coforecast/__init__.py
coforecast-0.0.0.dist-info/LICENSE
coforecast-0.0.0.dist-info/METADATA
coforecast-0.0.0.dist-info/WHEEL
coforecast-0.0.0.dist-info/top_level.txt
coforecast-0.0.0.dist-info/RECORD
