Metadata-Version: 2.1
Name: coforecast
Version: 0.0.0
Summary: Cardinal Operations Forecast
Home-page: UNKNOWN
Author: ['CoForecast Developers']
License: UNKNOWN
Platform: UNKNOWN
License-File: LICENSE
